{
  "updatedAt": "2026-07-05T06:06:55.157Z",
  "townSlug": "tonbridge",
  "countySlug": "kent",
  "isDistrictLevelFallback": false,
  "stats": {
    "medianPrice": 403625,
    "medianByType": {
      "D": 650000,
      "S": 415000,
      "T": 337000,
      "F": 225500
    },
    "transactionCount12m": 1448,
    "yoyChange": -2.7,
    "newBuildCount": 23,
    "existingCount": 1425,
    "newBuildPremium": 12.9
  },
  "recentTransactions": [
    {
      "price": 385000,
      "date": "2026-05-26",
      "postcode": "TN15 8RQ",
      "propertyType": "S",
      "newBuild": false,
      "tenure": "F",
      "address": "23, QUARRY HILL ROAD"
    },
    {
      "price": 237000,
      "date": "2026-05-22",
      "postcode": "ME20 7BP",
      "propertyType": "T",
      "newBuild": false,
      "tenure": "F",
      "address": "2, BUSH ROW"
    },
    {
      "price": 440000,
      "date": "2026-05-21",
      "postcode": "ME19 5QB",
      "propertyType": "D",
      "newBuild": false,
      "tenure": "F",
      "address": "15, WHEATFIELD"
    },
    {
      "price": 320000,
      "date": "2026-05-19",
      "postcode": "TN10 3EN",
      "propertyType": "T",
      "newBuild": false,
      "tenure": "F",
      "address": "13, DERNIER ROAD"
    },
    {
      "price": 265000,
      "date": "2026-05-18",
      "postcode": "ME6 5PE",
      "propertyType": "F",
      "newBuild": false,
      "tenure": "L",
      "address": "30, LAMBE CLOSE"
    },
    {
      "price": 425000,
      "date": "2026-05-15",
      "postcode": "ME19 4NJ",
      "propertyType": "S",
      "newBuild": false,
      "tenure": "F",
      "address": "8, LANGLEY WAY"
    },
    {
      "price": 240000,
      "date": "2026-05-15",
      "postcode": "ME19 4SJ",
      "propertyType": "F",
      "newBuild": false,
      "tenure": "L",
      "address": "27, MELROSE AVENUE"
    },
    {
      "price": 515000,
      "date": "2026-05-15",
      "postcode": "ME1 3TY",
      "propertyType": "D",
      "newBuild": false,
      "tenure": "F",
      "address": "227, HIGH STREET"
    },
    {
      "price": 385000,
      "date": "2026-05-15",
      "postcode": "TN11 0HJ",
      "propertyType": "T",
      "newBuild": false,
      "tenure": "F",
      "address": "8, TWYFORD ROAD"
    },
    {
      "price": 300000,
      "date": "2026-05-15",
      "postcode": "ME19 5RE",
      "propertyType": "T",
      "newBuild": false,
      "tenure": "F",
      "address": "30, WILLOWMEAD"
    },
    {
      "price": 420000,
      "date": "2026-05-15",
      "postcode": "TN9 2QN",
      "propertyType": "S",
      "newBuild": false,
      "tenure": "F",
      "address": "5, MOLESCROFT WAY"
    },
    {
      "price": 527000,
      "date": "2026-05-14",
      "postcode": "TN11 9BS",
      "propertyType": "S",
      "newBuild": false,
      "tenure": "F",
      "address": "2, TONBRIDGE ROAD"
    },
    {
      "price": 120000,
      "date": "2026-05-14",
      "postcode": "TN9 1GS",
      "propertyType": "F",
      "newBuild": false,
      "tenure": "L",
      "address": "1, HOLMES COURT, MEDWAY WHARF ROAD"
    },
    {
      "price": 460000,
      "date": "2026-05-14",
      "postcode": "TN11 0RT",
      "propertyType": "S",
      "newBuild": false,
      "tenure": "F",
      "address": "16, THE FORSTAL"
    },
    {
      "price": 575000,
      "date": "2026-05-12",
      "postcode": "TN11 9HB",
      "propertyType": "S",
      "newBuild": false,
      "tenure": "F",
      "address": "33, WEALDEN CLOSE"
    },
    {
      "price": 465000,
      "date": "2026-05-11",
      "postcode": "ME19 4QN",
      "propertyType": "S",
      "newBuild": false,
      "tenure": "F",
      "address": "38, PORTER AVENUE"
    },
    {
      "price": 267500,
      "date": "2026-05-11",
      "postcode": "ME20 6EE",
      "propertyType": "S",
      "newBuild": false,
      "tenure": "F",
      "address": "66, WOODLANDS ROAD"
    },
    {
      "price": 190000,
      "date": "2026-05-08",
      "postcode": "TN15 8HY",
      "propertyType": "F",
      "newBuild": false,
      "tenure": "L",
      "address": "8, HUNTS FARM CLOSE"
    },
    {
      "price": 575000,
      "date": "2026-05-08",
      "postcode": "ME19 4RF",
      "propertyType": "D",
      "newBuild": false,
      "tenure": "F",
      "address": "4, MITCHELL ROAD"
    },
    {
      "price": 440000,
      "date": "2026-05-08",
      "postcode": "ME19 4DF",
      "propertyType": "S",
      "newBuild": false,
      "tenure": "F",
      "address": "102, HAZEN ROAD"
    }
  ],
  "monthlyHistory": [
    {
      "month": "2024-01",
      "medianPrice": 380000,
      "transactions": 125
    },
    {
      "month": "2024-02",
      "medianPrice": 393610,
      "transactions": 120
    },
    {
      "month": "2024-03",
      "medianPrice": 383750,
      "transactions": 154
    },
    {
      "month": "2024-04",
      "medianPrice": 410000,
      "transactions": 144
    },
    {
      "month": "2024-05",
      "medianPrice": 394000,
      "transactions": 208
    },
    {
      "month": "2024-06",
      "medianPrice": 392998,
      "transactions": 170
    },
    {
      "month": "2024-07",
      "medianPrice": 390000,
      "transactions": 221
    },
    {
      "month": "2024-08",
      "medianPrice": 450000,
      "transactions": 201
    },
    {
      "month": "2024-09",
      "medianPrice": 417500,
      "transactions": 152
    },
    {
      "month": "2024-10",
      "medianPrice": 415000,
      "transactions": 231
    },
    {
      "month": "2024-11",
      "medianPrice": 403000,
      "transactions": 239
    },
    {
      "month": "2024-12",
      "medianPrice": 405000,
      "transactions": 203
    },
    {
      "month": "2025-01",
      "medianPrice": 410000,
      "transactions": 176
    },
    {
      "month": "2025-02",
      "medianPrice": 397000,
      "transactions": 171
    },
    {
      "month": "2025-03",
      "medianPrice": 410000,
      "transactions": 391
    },
    {
      "month": "2025-04",
      "medianPrice": 382500,
      "transactions": 96
    },
    {
      "month": "2025-05",
      "medianPrice": 448248,
      "transactions": 140
    },
    {
      "month": "2025-06",
      "medianPrice": 425000,
      "transactions": 184
    },
    {
      "month": "2025-07",
      "medianPrice": 425000,
      "transactions": 169
    },
    {
      "month": "2025-08",
      "medianPrice": 420000,
      "transactions": 185
    },
    {
      "month": "2025-09",
      "medianPrice": 390000,
      "transactions": 163
    },
    {
      "month": "2025-10",
      "medianPrice": 393000,
      "transactions": 195
    },
    {
      "month": "2025-11",
      "medianPrice": 395000,
      "transactions": 152
    },
    {
      "month": "2025-12",
      "medianPrice": 403500,
      "transactions": 139
    },
    {
      "month": "2026-01",
      "medianPrice": 404750,
      "transactions": 106
    },
    {
      "month": "2026-02",
      "medianPrice": 440000,
      "transactions": 93
    },
    {
      "month": "2026-03",
      "medianPrice": 400000,
      "transactions": 123
    },
    {
      "month": "2026-04",
      "medianPrice": 380000,
      "transactions": 106
    },
    {
      "month": "2026-05",
      "medianPrice": 380000,
      "transactions": 42
    }
  ],
  "quarterlyHistory": [
    {
      "quarter": "2024-Q1",
      "medianPrice": 386000,
      "transactions": 399
    },
    {
      "quarter": "2024-Q2",
      "medianPrice": 395000,
      "transactions": 522
    },
    {
      "quarter": "2024-Q3",
      "medianPrice": 417500,
      "transactions": 574
    },
    {
      "quarter": "2024-Q4",
      "medianPrice": 407040,
      "transactions": 673
    },
    {
      "quarter": "2025-Q1",
      "medianPrice": 406750,
      "transactions": 738
    },
    {
      "quarter": "2025-Q2",
      "medianPrice": 425000,
      "transactions": 420
    },
    {
      "quarter": "2025-Q3",
      "medianPrice": 412500,
      "transactions": 517
    },
    {
      "quarter": "2025-Q4",
      "medianPrice": 400000,
      "transactions": 486
    },
    {
      "quarter": "2026-Q1",
      "medianPrice": 410000,
      "transactions": 322
    },
    {
      "quarter": "2026-Q2",
      "medianPrice": 380000,
      "transactions": 148
    }
  ]
}