{
  "updatedAt": "2026-07-12T10:15:58.973Z",
  "townSlug": "huntingdon",
  "countySlug": "cambridgeshire",
  "localAuthority": "Huntingdonshire District Council",
  "source": "idox",
  "dataset": {
    "windowMonths": 1,
    "from": "2026-06-12",
    "to": "2026-07-12",
    "retrievedAt": "2026-07-12T10:15:58.972Z"
  },
  "summary": {
    "total": 154,
    "relevant": 26,
    "approved": 0,
    "pending": 25,
    "refused": 0,
    "approvedUnits": 0,
    "pendingUnits": 772,
    "totalUnits": 772,
    "approvedGdv": 0,
    "pendingGdv": 235846000,
    "totalEstimatedGDV": 235846000,
    "approvalRate": 0
  },
  "approvedApplications": [],
  "pendingApplications": [
    {
      "reference": "26/01236/COA",
      "address": "Bedford Borough Council Borough Hall Cauldwell Street Bedford MK42 9AP",
      "postcode": "MK42 9AP",
      "ward": "",
      "proposal": "Outline application (all matters reserved) for a mixed use phased and severable development, comprising residential (Use Class C2 and C3) development of up to 4,400 dwellings; commercial (Use Classes E, F1, F2, C1 and Sui Generis); public open space including sport and play facilities; education facilities comprising primary and secondary school provision (Use Class F1(a)); provision of Biodiversity Net Gain; transport and access infrastructure; a safeguarding zone for the delivery of East West Rail; retention, renovation and reuse of the on-site historic assets; and associated demolitions, parking, servicing, utilities, footpath and cycle links, drainage and other infrastructure.",
      "category": "other_residential",
      "units": 400,
      "estimatedGdv": 122200000,
      "status": "In progress",
      "decision": "In progress",
      "receivedDate": "07/07/2026",
      "decisionDate": "",
      "applicantName": "",
      "applicantCompany": "",
      "agentName": "",
      "agentCompany": "",
      "sourceUrl": "https://publicaccess.huntingdonshire.gov.uk/online-applications/applicationDetails.do?activeTab=summary&keyVal=THT4SVIK0QB00"
    },
    {
      "reference": "26/01224/FUL",
      "address": "Telephone Exchange St Johns Street Huntingdon PE29 3DF",
      "postcode": "PE29 3DF",
      "ward": "",
      "proposal": "The installation of 2 OMNI antenna at 34.65m, 1 cabinet, along with associated ancillary equipment and feeder cables.",
      "category": "other_relevant",
      "units": null,
      "estimatedGdv": null,
      "status": "In progress",
      "decision": "In progress",
      "receivedDate": "06/07/2026",
      "decisionDate": "",
      "applicantName": "",
      "applicantCompany": "",
      "agentName": "",
      "agentCompany": "",
      "sourceUrl": "https://publicaccess.huntingdonshire.gov.uk/online-applications/applicationDetails.do?activeTab=summary&keyVal=THQV6GIKG3000"
    },
    {
      "reference": "26/01231/FUL",
      "address": "Unit 17 Oakwood Business Park Old Great North Road Sawtry PE28 5XN",
      "postcode": "PE28 5XN",
      "ward": "",
      "proposal": "Installation of windows to rear.",
      "category": "other_relevant",
      "units": null,
      "estimatedGdv": null,
      "status": "In progress",
      "decision": "In progress",
      "receivedDate": "06/07/2026",
      "decisionDate": "",
      "applicantName": "",
      "applicantCompany": "",
      "agentName": "",
      "agentCompany": "",
      "sourceUrl": "https://publicaccess.huntingdonshire.gov.uk/online-applications/applicationDetails.do?activeTab=summary&keyVal=THSS5TIK0Q000"
    },
    {
      "reference": "26/01230/LBC",
      "address": "2 Blacksmiths Lane Abbotsley St Neots PE19 6UG",
      "postcode": "PE19 6UG",
      "ward": "",
      "proposal": "Erection of link extension and conversion of barn to provide additonal living space to existing cottage.",
      "category": "conversion",
      "units": null,
      "estimatedGdv": null,
      "status": "In progress",
      "decision": "In progress",
      "receivedDate": "06/07/2026",
      "decisionDate": "",
      "applicantName": "",
      "applicantCompany": "",
      "agentName": "",
      "agentCompany": "",
      "sourceUrl": "https://publicaccess.huntingdonshire.gov.uk/online-applications/applicationDetails.do?activeTab=summary&keyVal=THSRR3IK0Q000"
    },
    {
      "reference": "26/01223/LBC",
      "address": "10 East Street Great Gransden Sandy SG19 3AB",
      "postcode": "SG19 3AB",
      "ward": "",
      "proposal": "Single-storey extension to the rear, including the demolition of existing conservatory and existing rear extension, and minor internal reconfiguration and refurbishment works.",
      "category": "other_relevant",
      "units": null,
      "estimatedGdv": null,
      "status": "In progress",
      "decision": "In progress",
      "receivedDate": "06/07/2026",
      "decisionDate": "",
      "applicantName": "",
      "applicantCompany": "",
      "agentName": "",
      "agentCompany": "",
      "sourceUrl": "https://publicaccess.huntingdonshire.gov.uk/online-applications/applicationDetails.do?activeTab=summary&keyVal=THQMY9IKG2T00"
    },
    {
      "reference": "26/01218/S73",
      "address": "34 The Broadway St Ives PE27 5BN",
      "postcode": "PE27 5BN",
      "ward": "",
      "proposal": "Variation of Condition 3 (Opening Hours) of 25/01717/FUL to extend opening hours to midnight on Thursdays and 1am on Fridays and Saturdays.",
      "category": "other_relevant",
      "units": null,
      "estimatedGdv": null,
      "status": "In progress",
      "decision": "In progress",
      "receivedDate": "06/07/2026",
      "decisionDate": "",
      "applicantName": "",
      "applicantCompany": "",
      "agentName": "",
      "agentCompany": "",
      "sourceUrl": "https://publicaccess.huntingdonshire.gov.uk/online-applications/applicationDetails.do?activeTab=summary&keyVal=THQMXGIKG2K00"
    },
    {
      "reference": "26/01225/PIP",
      "address": "6 Brook Farm Drive Colne Huntingdon PE28 3PD",
      "postcode": "PE28 3PD",
      "ward": "",
      "proposal": "Permission in Principle for a single dwelling",
      "category": "other_relevant",
      "units": 1,
      "estimatedGdv": 305500,
      "status": "In progress",
      "decision": "In progress",
      "receivedDate": "06/07/2026",
      "decisionDate": "",
      "applicantName": "",
      "applicantCompany": "",
      "agentName": "",
      "agentCompany": "",
      "sourceUrl": "https://publicaccess.huntingdonshire.gov.uk/online-applications/applicationDetails.do?activeTab=summary&keyVal=THR4G4IK0NY00"
    },
    {
      "reference": "26/01204/S73",
      "address": "GSN Conservatories The Town Great Staughton St Neots PE19 5BE",
      "postcode": "PE19 5BE",
      "ward": "",
      "proposal": "Removal of Condition 24 (Restrict Occupation to Existing Business) of 25/00225/FUL",
      "category": "other_relevant",
      "units": null,
      "estimatedGdv": null,
      "status": "In progress",
      "decision": "In progress",
      "receivedDate": "03/07/2026",
      "decisionDate": "",
      "applicantName": "",
      "applicantCompany": "",
      "agentName": "",
      "agentCompany": "",
      "sourceUrl": "https://publicaccess.huntingdonshire.gov.uk/online-applications/applicationDetails.do?activeTab=summary&keyVal=THLHL4IK0QB00"
    },
    {
      "reference": "26/01194/OUT",
      "address": "Land West Of Toll Bar Way Sawtry",
      "postcode": "",
      "ward": "",
      "proposal": "Outline planning permission for phased development of up to 330 dwellings with all matters reserved except access from Toll Bar Way and Green End Road, public open space and play area, landscaping, sustainable drainage infrastructure and associated infrastructure.",
      "category": "other_relevant",
      "units": 330,
      "estimatedGdv": 100815000,
      "status": "In progress",
      "decision": "In progress",
      "receivedDate": "02/07/2026",
      "decisionDate": "",
      "applicantName": "",
      "applicantCompany": "",
      "agentName": "",
      "agentCompany": "",
      "sourceUrl": "https://publicaccess.huntingdonshire.gov.uk/online-applications/applicationDetails.do?activeTab=summary&keyVal=THJRKOIKG0L00"
    },
    {
      "reference": "26/01184/FUL",
      "address": "Units 5 And 6 Meadow Park Meadow Lane St Ives PE27 4LG",
      "postcode": "PE27 4LG",
      "ward": "",
      "proposal": "Erection of 4 dormers and alterations and replacement of existing windows and cladding",
      "category": "other_relevant",
      "units": null,
      "estimatedGdv": null,
      "status": "In progress",
      "decision": "In progress",
      "receivedDate": "01/07/2026",
      "decisionDate": "",
      "applicantName": "",
      "applicantCompany": "",
      "agentName": "",
      "agentCompany": "",
      "sourceUrl": "https://publicaccess.huntingdonshire.gov.uk/online-applications/applicationDetails.do?activeTab=summary&keyVal=THHUAQIKFZI00"
    },
    {
      "reference": "26/01178/LBC",
      "address": "The Haycock Hotel London Road Wansford Peterborough PE8 6JA",
      "postcode": "PE8 6JA",
      "ward": "",
      "proposal": "Proposed re-roofing of the Grade II listed barn.",
      "category": "other_relevant",
      "units": null,
      "estimatedGdv": null,
      "status": "In progress",
      "decision": "In progress",
      "receivedDate": "30/06/2026",
      "decisionDate": "",
      "applicantName": "",
      "applicantCompany": "",
      "agentName": "",
      "agentCompany": "",
      "sourceUrl": "https://publicaccess.huntingdonshire.gov.uk/online-applications/applicationDetails.do?activeTab=summary&keyVal=THFZDUIKFYJ00"
    },
    {
      "reference": "26/01169/S73",
      "address": "The Orchard Garden Farm The Town Great Staughton St Neots PE19 5BE",
      "postcode": "PE19 5BE",
      "ward": "",
      "proposal": "Variation of condition 8 (deliveries and dispatches) of 25/02081/S73 to alter delivery/collection times on weekdays to 04:00 to 20:00 and 07:00 to 13:30 on Saturdays to reflect the operational requirements of the site",
      "category": "other_relevant",
      "units": null,
      "estimatedGdv": null,
      "status": "In progress",
      "decision": "In progress",
      "receivedDate": "29/06/2026",
      "decisionDate": "",
      "applicantName": "",
      "applicantCompany": "",
      "agentName": "",
      "agentCompany": "",
      "sourceUrl": "https://publicaccess.huntingdonshire.gov.uk/online-applications/applicationDetails.do?activeTab=summary&keyVal=THEAGEIKFXM00"
    },
    {
      "reference": "26/01162/S73",
      "address": "Glen Eden Potton Road Abbotsley St Neots PE19 6XJ",
      "postcode": "PE19 6XJ",
      "ward": "",
      "proposal": "Removal of Condition 4 (remain ancillary) of 17/00988/HHFUL.",
      "category": "other_relevant",
      "units": null,
      "estimatedGdv": null,
      "status": "In progress",
      "decision": "In progress",
      "receivedDate": "29/06/2026",
      "decisionDate": "",
      "applicantName": "",
      "applicantCompany": "",
      "agentName": "",
      "agentCompany": "",
      "sourceUrl": "https://publicaccess.huntingdonshire.gov.uk/online-applications/applicationDetails.do?activeTab=summary&keyVal=THDOA4IKFWU00"
    },
    {
      "reference": "26/01152/OUT",
      "address": "Hankins Garage 46 Whytefield Road Ramsey Huntingdon PE26 1AH",
      "postcode": "PE26 1AH",
      "ward": "",
      "proposal": "Proposed outline application for development of up to 19 residential dwellings with matters committed to access",
      "category": "other_relevant",
      "units": 19,
      "estimatedGdv": 5804500,
      "status": "In progress",
      "decision": "In progress",
      "receivedDate": "25/06/2026",
      "decisionDate": "",
      "applicantName": "",
      "applicantCompany": "",
      "agentName": "",
      "agentCompany": "",
      "sourceUrl": "https://publicaccess.huntingdonshire.gov.uk/online-applications/applicationDetails.do?activeTab=summary&keyVal=TH6YJJIKFVP00"
    },
    {
      "reference": "26/01140/FUL",
      "address": "15 Blackstone Road Huntingdon PE29 6EF",
      "postcode": "PE29 6EF",
      "ward": "",
      "proposal": "Change of Use to General Industrial Use including installation of MOT Testing Facility and Spray Booth (B8)",
      "category": "change_of_use",
      "units": null,
      "estimatedGdv": null,
      "status": "In progress",
      "decision": "In progress",
      "receivedDate": "24/06/2026",
      "decisionDate": "",
      "applicantName": "",
      "applicantCompany": "",
      "agentName": "",
      "agentCompany": "",
      "sourceUrl": "https://publicaccess.huntingdonshire.gov.uk/online-applications/applicationDetails.do?activeTab=summary&keyVal=TH4QONIK0NY00"
    },
    {
      "reference": "26/01136/S73",
      "address": "New Manor Farm Sawtry Way Wyton Huntingdon PE28 2DY",
      "postcode": "PE28 2DY",
      "ward": "",
      "proposal": "Variation of conditions 2 (approved plans) and 3 (materials) of 24/02369/HHFUL (Conversion of garage to provide gym and office space and construction of rear conservatory to converted garage)",
      "category": "conversion",
      "units": null,
      "estimatedGdv": null,
      "status": "In progress",
      "decision": "In progress",
      "receivedDate": "23/06/2026",
      "decisionDate": "",
      "applicantName": "",
      "applicantCompany": "",
      "agentName": "",
      "agentCompany": "",
      "sourceUrl": "https://publicaccess.huntingdonshire.gov.uk/online-applications/applicationDetails.do?activeTab=summary&keyVal=TH36EPIKFTQ00"
    },
    {
      "reference": "26/01133/PIP",
      "address": "Land Adjacent 12 High Street Great Paxton",
      "postcode": "",
      "ward": "",
      "proposal": "Permission in principle for up to 9 dwellings",
      "category": "other_relevant",
      "units": 9,
      "estimatedGdv": 2749500,
      "status": "In progress",
      "decision": "In progress",
      "receivedDate": "22/06/2026",
      "decisionDate": "",
      "applicantName": "",
      "applicantCompany": "",
      "agentName": "",
      "agentCompany": "",
      "sourceUrl": "https://publicaccess.huntingdonshire.gov.uk/online-applications/applicationDetails.do?activeTab=summary&keyVal=TH1GIXIK0QB00"
    },
    {
      "reference": "26/01123/S73",
      "address": "Car Mart Station Bridge Broadway Yaxley Peterborough PE7 3EL",
      "postcode": "PE7 3EL",
      "ward": "",
      "proposal": "Variation of Condition 2 (Approved plans) and Removal of Conditions 4 (Contamination - Phase 1 Desk Study), 5 (Contamination - Phase 2 and 3), 6 (Contamination - Remediation) & 7 (Contamination - Phase 4) of 23/01832/FUL.",
      "category": "other_relevant",
      "units": null,
      "estimatedGdv": null,
      "status": "In progress",
      "decision": "In progress",
      "receivedDate": "22/06/2026",
      "decisionDate": "",
      "applicantName": "",
      "applicantCompany": "",
      "agentName": "",
      "agentCompany": "",
      "sourceUrl": "https://publicaccess.huntingdonshire.gov.uk/online-applications/applicationDetails.do?activeTab=summary&keyVal=TH0PIKIKFS900"
    },
    {
      "reference": "26/01121/FUL",
      "address": "Waters Edge Elton Road Wansford",
      "postcode": "",
      "ward": "",
      "proposal": "Erection of single dwelling",
      "category": "new_build",
      "units": 1,
      "estimatedGdv": 305500,
      "status": "In progress",
      "decision": "In progress",
      "receivedDate": "22/06/2026",
      "decisionDate": "",
      "applicantName": "",
      "applicantCompany": "",
      "agentName": "",
      "agentCompany": "",
      "sourceUrl": "https://publicaccess.huntingdonshire.gov.uk/online-applications/applicationDetails.do?activeTab=summary&keyVal=TH0PCSIKFS400"
    },
    {
      "reference": "26/01106/S73",
      "address": "Land West Of Longlands Close And North Of The Paddock Caravan Park Ramsey Road Warboys",
      "postcode": "",
      "ward": "",
      "proposal": "Variation of condition 1 (approved plans) of 23/02505/REM",
      "category": "other_relevant",
      "units": null,
      "estimatedGdv": null,
      "status": "In progress",
      "decision": "In progress",
      "receivedDate": "19/06/2026",
      "decisionDate": "",
      "applicantName": "",
      "applicantCompany": "",
      "agentName": "",
      "agentCompany": "",
      "sourceUrl": "https://publicaccess.huntingdonshire.gov.uk/online-applications/applicationDetails.do?activeTab=summary&keyVal=TGV5GGIKFQN00"
    },
    {
      "reference": "26/01081/FUL",
      "address": "Land Rear Of 72A To 78 High Street Great Paxton",
      "postcode": "",
      "ward": "",
      "proposal": "Erection of 9 new dwellings (Use Class C3) with associated vehicular and pedestrian access via the approved development (19/00959/FUL)",
      "category": "new_build",
      "units": 9,
      "estimatedGdv": 2749500,
      "status": "In progress",
      "decision": "In progress",
      "receivedDate": "15/06/2026",
      "decisionDate": "",
      "applicantName": "",
      "applicantCompany": "",
      "agentName": "",
      "agentCompany": "",
      "sourceUrl": "https://publicaccess.huntingdonshire.gov.uk/online-applications/applicationDetails.do?activeTab=summary&keyVal=TGO1UXIKFNA00"
    },
    {
      "reference": "26/01076/LBC",
      "address": "Units 4 And 5 Cromwell Court High Street Kimbolton Huntingdon PE28 0HA",
      "postcode": "PE28 0HA",
      "ward": "",
      "proposal": "Single storey extension and associated works",
      "category": "other_relevant",
      "units": null,
      "estimatedGdv": null,
      "status": "In progress",
      "decision": "In progress",
      "receivedDate": "15/06/2026",
      "decisionDate": "",
      "applicantName": "",
      "applicantCompany": "",
      "agentName": "",
      "agentCompany": "",
      "sourceUrl": "https://publicaccess.huntingdonshire.gov.uk/online-applications/applicationDetails.do?activeTab=summary&keyVal=TGNQUSIKFMQ00"
    },
    {
      "reference": "26/01075/FUL",
      "address": "Units 4 And 5 Cromwell Court High Street Kimbolton Huntingdon PE28 0HA",
      "postcode": "PE28 0HA",
      "ward": "",
      "proposal": "Single storey extension and associated works",
      "category": "other_relevant",
      "units": null,
      "estimatedGdv": null,
      "status": "In progress",
      "decision": "In progress",
      "receivedDate": "15/06/2026",
      "decisionDate": "",
      "applicantName": "",
      "applicantCompany": "",
      "agentName": "",
      "agentCompany": "",
      "sourceUrl": "https://publicaccess.huntingdonshire.gov.uk/online-applications/applicationDetails.do?activeTab=summary&keyVal=TGNQURIKFMP00"
    },
    {
      "reference": "26/01067/S73",
      "address": "Tilford Station Road Tilbrook Huntingdon PE28 0JT",
      "postcode": "PE28 0JT",
      "ward": "",
      "proposal": "Variation of condition 2 (Plans listed in table above) of 15/01550/FUL.",
      "category": "other_relevant",
      "units": null,
      "estimatedGdv": null,
      "status": "In progress",
      "decision": "In progress",
      "receivedDate": "12/06/2026",
      "decisionDate": "",
      "applicantName": "",
      "applicantCompany": "",
      "agentName": "",
      "agentCompany": "",
      "sourceUrl": "https://publicaccess.huntingdonshire.gov.uk/online-applications/applicationDetails.do?activeTab=summary&keyVal=TGIHSWIKFLZ00"
    },
    {
      "reference": "26/01071/PIP",
      "address": "Land Left Of The Paddock Warboys Road Pidley",
      "postcode": "",
      "ward": "",
      "proposal": "Permission in Principle for 2-3 dwellings",
      "category": "other_relevant",
      "units": 3,
      "estimatedGdv": 916500,
      "status": "In progress",
      "decision": "In progress",
      "receivedDate": "12/06/2026",
      "decisionDate": "",
      "applicantName": "",
      "applicantCompany": "",
      "agentName": "",
      "agentCompany": "",
      "sourceUrl": "https://publicaccess.huntingdonshire.gov.uk/online-applications/applicationDetails.do?activeTab=summary&keyVal=TGIR2WIK0NY00"
    }
  ]
}