{
  "updatedAt": "2026-04-08T05:17:06.057Z",
  "townSlug": "sevenoaks",
  "countySlug": "kent",
  "stats": {
    "medianPrice": 485000,
    "medianByType": {
      "D": 830000,
      "S": 510000,
      "T": 375000,
      "F": 259500
    },
    "transactionCount12m": 1130,
    "yoyChange": 4.3,
    "newBuildCount": 7,
    "existingCount": 1123,
    "newBuildPremium": 33.7
  },
  "recentTransactions": [
    {
      "price": 130000,
      "date": "2026-02-24",
      "postcode": "BR8 7PB",
      "propertyType": "O",
      "newBuild": false,
      "tenure": "F",
      "address": "7, SHIP LANE"
    },
    {
      "price": 880000,
      "date": "2026-02-18",
      "postcode": "TN15 0ED",
      "propertyType": "T",
      "newBuild": false,
      "tenure": "F",
      "address": "3, THE STABLES, WILDERNESSE AVENUE"
    },
    {
      "price": 780000,
      "date": "2026-02-17",
      "postcode": "TN14 5GE",
      "propertyType": "D",
      "newBuild": false,
      "tenure": "F",
      "address": "15, YEW TREE ROAD"
    },
    {
      "price": 535000,
      "date": "2026-02-16",
      "postcode": "DA3 7EA",
      "propertyType": "S",
      "newBuild": false,
      "tenure": "F",
      "address": "COPPERFIELD, QUAKERS CLOSE"
    },
    {
      "price": 263500,
      "date": "2026-02-16",
      "postcode": "TN8 5BD",
      "propertyType": "S",
      "newBuild": false,
      "tenure": "F",
      "address": "14, CHURCH STREET"
    },
    {
      "price": 775000,
      "date": "2026-02-16",
      "postcode": "TN14 7SW",
      "propertyType": "D",
      "newBuild": false,
      "tenure": "F",
      "address": "SEPTEMBER COTTAGE, CHURCH STREET"
    },
    {
      "price": 535000,
      "date": "2026-02-16",
      "postcode": "BR8 8LP",
      "propertyType": "S",
      "newBuild": false,
      "tenure": "F",
      "address": "TINTAGEL, CRAY ROAD"
    },
    {
      "price": 900000,
      "date": "2026-02-16",
      "postcode": "TN3 0RT",
      "propertyType": "D",
      "newBuild": false,
      "tenure": "F",
      "address": "MEADOW VIEW HOUSE, FORDCOMBE ROAD"
    },
    {
      "price": 405000,
      "date": "2026-02-13",
      "postcode": "BR8 8AP",
      "propertyType": "S",
      "newBuild": false,
      "tenure": "F",
      "address": "53, LEECHCROFT AVENUE"
    },
    {
      "price": 405000,
      "date": "2026-02-13",
      "postcode": "TN11 8QB",
      "propertyType": "T",
      "newBuild": false,
      "tenure": "F",
      "address": "15, GARDEN COTTAGES"
    },
    {
      "price": 510500,
      "date": "2026-02-12",
      "postcode": "BR8 8NZ",
      "propertyType": "S",
      "newBuild": false,
      "tenure": "F",
      "address": "67, CRANLEIGH DRIVE"
    },
    {
      "price": 205000,
      "date": "2026-02-12",
      "postcode": "DA4 9LT",
      "propertyType": "F",
      "newBuild": false,
      "tenure": "L",
      "address": "36, GORRINGE AVENUE"
    },
    {
      "price": 1045000,
      "date": "2026-02-11",
      "postcode": "DA4 0EY",
      "propertyType": "D",
      "newBuild": false,
      "tenure": "F",
      "address": "15, ST MARTINS DRIVE"
    },
    {
      "price": 347500,
      "date": "2026-02-11",
      "postcode": "TN14 5DU",
      "propertyType": "T",
      "newBuild": false,
      "tenure": "F",
      "address": "135, CRAMPTONS ROAD"
    },
    {
      "price": 378750,
      "date": "2026-02-11",
      "postcode": "BR8 8TG",
      "propertyType": "T",
      "newBuild": false,
      "tenure": "F",
      "address": "7, BREMNER CLOSE"
    },
    {
      "price": 630000,
      "date": "2026-02-10",
      "postcode": "TN15 7JL",
      "propertyType": "D",
      "newBuild": false,
      "tenure": "F",
      "address": "ROSE HOUSE, GRAVESEND ROAD"
    },
    {
      "price": 280000,
      "date": "2026-02-10",
      "postcode": "TN13 2XR",
      "propertyType": "T",
      "newBuild": false,
      "tenure": "F",
      "address": "2, DARENTH MEWS"
    },
    {
      "price": 610000,
      "date": "2026-02-06",
      "postcode": "TN14 5JZ",
      "propertyType": "S",
      "newBuild": false,
      "tenure": "F",
      "address": "45, TELSTON LANE"
    },
    {
      "price": 500000,
      "date": "2026-02-06",
      "postcode": "DA3 8AR",
      "propertyType": "S",
      "newBuild": false,
      "tenure": "F",
      "address": "59, SPRINGCROFT"
    },
    {
      "price": 98000,
      "date": "2026-02-06",
      "postcode": "TN8 5FD",
      "propertyType": "F",
      "newBuild": false,
      "tenure": "L",
      "address": "APARTMENT 22, EADHELM COURT, PENLEE CLOSE"
    }
  ]
}