{
  "updatedAt": "2026-04-23T10:19:24.053Z",
  "townSlug": "burton-upon-trent",
  "countySlug": "staffordshire",
  "stats": {
    "medianPrice": 230000,
    "medianByType": {
      "D": 353227,
      "S": 220000,
      "T": 157250,
      "F": 96500
    },
    "transactionCount12m": 1340,
    "yoyChange": 0,
    "newBuildCount": 53,
    "existingCount": 1287,
    "newBuildPremium": 34.2
  },
  "recentTransactions": [
    {
      "price": 180000,
      "date": "2026-02-20",
      "postcode": "DE13 9TQ",
      "propertyType": "S",
      "newBuild": false,
      "tenure": "F",
      "address": "58, HENHURST RIDGE"
    },
    {
      "price": 490000,
      "date": "2026-02-19",
      "postcode": "DE13 9QP",
      "propertyType": "D",
      "newBuild": false,
      "tenure": "F",
      "address": "241, BEAMHILL ROAD"
    },
    {
      "price": 185000,
      "date": "2026-02-18",
      "postcode": "DE13 9LF",
      "propertyType": "S",
      "newBuild": false,
      "tenure": "F",
      "address": "91, HOLTS LANE"
    },
    {
      "price": 280000,
      "date": "2026-02-18",
      "postcode": "DE13 9AF",
      "propertyType": "S",
      "newBuild": false,
      "tenure": "F",
      "address": "4, CROFT CLOSE"
    },
    {
      "price": 345000,
      "date": "2026-02-16",
      "postcode": "ST14 5AW",
      "propertyType": "D",
      "newBuild": false,
      "tenure": "F",
      "address": "6, BARNWELL CLOSE"
    },
    {
      "price": 150000,
      "date": "2026-02-13",
      "postcode": "DE14 3NB",
      "propertyType": "T",
      "newBuild": false,
      "tenure": "F",
      "address": "40, BROADWAY STREET"
    },
    {
      "price": 188000,
      "date": "2026-02-13",
      "postcode": "DE14 2FR",
      "propertyType": "T",
      "newBuild": false,
      "tenure": "L",
      "address": "59, UPTON DRIVE"
    },
    {
      "price": 357000,
      "date": "2026-02-13",
      "postcode": "DE15 0BA",
      "propertyType": "D",
      "newBuild": false,
      "tenure": "F",
      "address": "79, MILL HILL LANE"
    },
    {
      "price": 115000,
      "date": "2026-02-12",
      "postcode": "DE14 2HY",
      "propertyType": "T",
      "newBuild": false,
      "tenure": "F",
      "address": "44, GORDON STREET"
    },
    {
      "price": 642000,
      "date": "2026-02-12",
      "postcode": "WS15 3FB",
      "propertyType": "D",
      "newBuild": false,
      "tenure": "F",
      "address": "10, IVY CLOSE"
    },
    {
      "price": 157500,
      "date": "2026-02-12",
      "postcode": "DE14 1TU",
      "propertyType": "T",
      "newBuild": false,
      "tenure": "F",
      "address": "16, BLYTHFIELD"
    },
    {
      "price": 420000,
      "date": "2026-02-12",
      "postcode": "DE13 8JG",
      "propertyType": "D",
      "newBuild": false,
      "tenure": "F",
      "address": "51, WALES LANE"
    },
    {
      "price": 1080000,
      "date": "2026-02-11",
      "postcode": "DE13 8SU",
      "propertyType": "D",
      "newBuild": false,
      "tenure": "F",
      "address": "FOXLEIGH MEADOW, YOXALL ROAD"
    },
    {
      "price": 1150000,
      "date": "2026-02-11",
      "postcode": "DE13 8SW",
      "propertyType": "D",
      "newBuild": false,
      "tenure": "F",
      "address": "BRICKHILL FARM, BRICKHILL LANE"
    },
    {
      "price": 265000,
      "date": "2026-02-11",
      "postcode": "DE13 0RX",
      "propertyType": "S",
      "newBuild": false,
      "tenure": "F",
      "address": "12, HARBURY STREET"
    },
    {
      "price": 290000,
      "date": "2026-02-09",
      "postcode": "DE13 9HZ",
      "propertyType": "D",
      "newBuild": false,
      "tenure": "F",
      "address": "21, CROMWELL CLOSE"
    },
    {
      "price": 282000,
      "date": "2026-02-09",
      "postcode": "DE13 0RL",
      "propertyType": "D",
      "newBuild": false,
      "tenure": "F",
      "address": "1, WATERTON CLOSE"
    },
    {
      "price": 115000,
      "date": "2026-02-06",
      "postcode": "ST14 7QT",
      "propertyType": "T",
      "newBuild": false,
      "tenure": "F",
      "address": "37, JOHN STREET"
    },
    {
      "price": 151500,
      "date": "2026-02-06",
      "postcode": "DE13 0FB",
      "propertyType": "S",
      "newBuild": false,
      "tenure": "F",
      "address": "93, BRITANNIA DRIVE"
    },
    {
      "price": 160000,
      "date": "2026-02-06",
      "postcode": "ST14 7RH",
      "propertyType": "T",
      "newBuild": false,
      "tenure": "F",
      "address": "16, PARVA COURT"
    }
  ]
}