{
  "updatedAt": "2026-04-23T10:19:24.796Z",
  "townSlug": "leiston",
  "countySlug": "suffolk",
  "stats": {
    "medianPrice": 251500,
    "medianByType": {
      "D": 365000,
      "S": 253500,
      "T": 200000,
      "F": 133750
    },
    "transactionCount12m": 78,
    "yoyChange": 7.5,
    "newBuildCount": 0,
    "existingCount": 78,
    "newBuildPremium": -100
  },
  "recentTransactions": [
    {
      "price": 440000,
      "date": "2026-02-18",
      "postcode": "IP16 4PH",
      "propertyType": "D",
      "newBuild": false,
      "tenure": "F",
      "address": "HERITAGE HOUSE, THE SANCTUARY"
    },
    {
      "price": 250000,
      "date": "2026-02-12",
      "postcode": "IP16 4PD",
      "propertyType": "D",
      "newBuild": false,
      "tenure": "F",
      "address": "VIKINGS WAY, NORTH END AVENUE"
    },
    {
      "price": 257000,
      "date": "2026-02-06",
      "postcode": "IP16 4LF",
      "propertyType": "S",
      "newBuild": false,
      "tenure": "F",
      "address": "17, GARRETT CRESCENT"
    },
    {
      "price": 365000,
      "date": "2026-02-06",
      "postcode": "IP16 4PW",
      "propertyType": "S",
      "newBuild": false,
      "tenure": "F",
      "address": "2, MEADOWSIDE, ALDEBURGH ROAD"
    },
    {
      "price": 330000,
      "date": "2026-01-30",
      "postcode": "IP16 4FN",
      "propertyType": "D",
      "newBuild": false,
      "tenure": "F",
      "address": "9, OAK DRIVE"
    },
    {
      "price": 160000,
      "date": "2026-01-09",
      "postcode": "IP16 4AL",
      "propertyType": "T",
      "newBuild": false,
      "tenure": "F",
      "address": "3, PROSPECT PLACE"
    },
    {
      "price": 285000,
      "date": "2026-01-09",
      "postcode": "IP16 4JG",
      "propertyType": "S",
      "newBuild": false,
      "tenure": "F",
      "address": "58, KING GEORGES AVENUE"
    },
    {
      "price": 265000,
      "date": "2026-01-08",
      "postcode": "IP16 4AY",
      "propertyType": "T",
      "newBuild": false,
      "tenure": "F",
      "address": "12, EASTWARD HO"
    },
    {
      "price": 210000,
      "date": "2026-01-08",
      "postcode": "IP16 4AR",
      "propertyType": "T",
      "newBuild": false,
      "tenure": "F",
      "address": "9, ARCHWAY COTTAGES, VALLEY ROAD"
    },
    {
      "price": 132500,
      "date": "2026-01-05",
      "postcode": "IP16 4JD",
      "propertyType": "F",
      "newBuild": false,
      "tenure": "L",
      "address": "SUITE 2, COLONIAL HOUSE, MASTER LORD INDUSTRIAL ESTATE"
    },
    {
      "price": 495000,
      "date": "2025-12-19",
      "postcode": "IP16 4FF",
      "propertyType": "T",
      "newBuild": false,
      "tenure": "F",
      "address": "4, OAKS COURT"
    },
    {
      "price": 162500,
      "date": "2025-12-19",
      "postcode": "IP16 4WF",
      "propertyType": "S",
      "newBuild": false,
      "tenure": "L",
      "address": "108, HODGSON AVENUE"
    },
    {
      "price": 425000,
      "date": "2025-12-18",
      "postcode": "IP16 4UU",
      "propertyType": "D",
      "newBuild": false,
      "tenure": "F",
      "address": "5, HODGSON AVENUE"
    },
    {
      "price": 475000,
      "date": "2025-12-10",
      "postcode": "IP16 4JY",
      "propertyType": "D",
      "newBuild": false,
      "tenure": "F",
      "address": "7, ALDEBURGH ROAD"
    },
    {
      "price": 340000,
      "date": "2025-12-04",
      "postcode": "IP16 4LU",
      "propertyType": "S",
      "newBuild": false,
      "tenure": "F",
      "address": "2, THE FOLLIES"
    },
    {
      "price": 260000,
      "date": "2025-11-28",
      "postcode": "IP16 4JG",
      "propertyType": "S",
      "newBuild": false,
      "tenure": "F",
      "address": "50, KING GEORGES AVENUE"
    },
    {
      "price": 300000,
      "date": "2025-11-25",
      "postcode": "IP16 4JG",
      "propertyType": "D",
      "newBuild": false,
      "tenure": "F",
      "address": "54A, KING GEORGES AVENUE"
    },
    {
      "price": 190000,
      "date": "2025-11-20",
      "postcode": "IP16 4DJ",
      "propertyType": "T",
      "newBuild": false,
      "tenure": "F",
      "address": "35A, HAYLINGS ROAD"
    },
    {
      "price": 130000,
      "date": "2025-10-29",
      "postcode": "IP16 4DS",
      "propertyType": "T",
      "newBuild": false,
      "tenure": "F",
      "address": "63, HAYLINGS ROAD"
    },
    {
      "price": 253000,
      "date": "2025-10-27",
      "postcode": "IP16 4AY",
      "propertyType": "T",
      "newBuild": false,
      "tenure": "F",
      "address": "13, EASTWARD HO"
    }
  ]
}